streamlit_select_image/__init__.py
streamlit_select_image/frontend/build/asset-manifest.json
streamlit_select_image/frontend/build/bootstrap.min.css
streamlit_select_image/frontend/build/index.html
streamlit_select_image/frontend/build/precache-manifest.d3c814fff1eb120bd5b472739879dc35.js
streamlit_select_image/frontend/build/service-worker.js
streamlit_select_image/frontend/build/static/js/2.e971e80c.chunk.js
streamlit_select_image/frontend/build/static/js/2.e971e80c.chunk.js.LICENSE.txt
streamlit_select_image/frontend/build/static/js/2.e971e80c.chunk.js.map
streamlit_select_image/frontend/build/static/js/main.c39050d5.chunk.js
streamlit_select_image/frontend/build/static/js/main.c39050d5.chunk.js.map
streamlit_select_image/frontend/build/static/js/runtime-main.182a64f4.js
streamlit_select_image/frontend/build/static/js/runtime-main.182a64f4.js.map
streamlit_select_image/frontend/build/static/media/nothing.a83d55a4.png
streamlit_select_image-0.0.1.dist-info/LICENSE
streamlit_select_image-0.0.1.dist-info/METADATA
streamlit_select_image-0.0.1.dist-info/WHEEL
streamlit_select_image-0.0.1.dist-info/top_level.txt
streamlit_select_image-0.0.1.dist-info/RECORD
