Metadata-Version: 2.1
Name: streamlit-select-image
Version: 0.0.1
Summary: Simple Streamlit MUI Select with images.
Home-page: https://github.com/victorC97/streamlit_select_image
Author: victorC97
Author-email: victor.cour@telecomnancy.net
License: UNKNOWN
Platform: UNKNOWN
Requires-Python: >=3.6
License-File: LICENSE
Requires-Dist: streamlit (>=0.63)
